{"packaged_accessories_t1_8_0": 0, "packaged_accessories_t1_8_1": 0, "packaged_accessories_t1_8_2": 0, "packaged_accessories_t1_8_3": 0, "packaged_accessories_t1_8_4": 0, "packaged_accessories_t1_8_5": 0, "packaged_accessories_t1_8_6": 0, "packaged_accessories_t1_8_7": 0, "packaged_accessories_t1_8_8": 0, "packaged_accessories_t1_8_9": 0, "packaged_accessories_t1_8_10": 0, "packaged_accessories_t1_8_11": 0, "packaged_accessories_t1_8_12": 0, "packaged_accessories_t1_8_13": 0, "packaged_accessories_t1_8_14": 0, "packaged_accessories_t1_8_15": 0, "packaged_accessories_t1_8_16": 0, "packaged_accessories_t1_8_17": 0, "packaged_accessories_t1_8_18": 0, "packaged_accessories_t1_8_19": 0, "packaged_accessories_t1_9_0": 0, "packaged_accessories_t1_9_1": 0, "packaged_accessories_t1_9_2": 0, "packaged_accessories_t1_9_3": 0, "packaged_accessories_t1_9_4": 0, "packaged_accessories_t1_9_5": 0, "packaged_accessories_t1_9_6": 0, "packaged_accessories_t1_9_7": 0, "packaged_accessories_t1_9_8": 0, "packaged_accessories_t1_9_9": 0, "packaged_accessories_t1_9_10": 0, "packaged_accessories_t1_9_11": 0, "packaged_accessories_t1_9_12": 0, "packaged_accessories_t1_9_13": 0, "packaged_accessories_t1_9_14": 0, "packaged_accessories_t1_9_15": 0, "packaged_accessories_t1_9_16": 0, "packaged_accessories_t1_9_17": 0, "packaged_accessories_t1_9_18": 0, "packaged_accessories_t1_9_19": 0, "packaged_accessories_t1_14_0": 0, "packaged_accessories_t1_14_1": 0, "packaged_accessories_t1_14_2": 0, "packaged_accessories_t1_14_3": 0, "packaged_accessories_t1_14_4": 0, "packaged_accessories_t1_14_5": 0, "packaged_accessories_t1_14_6": 0, "packaged_accessories_t1_14_7": 0, "packaged_accessories_t1_14_8": 0, "packaged_accessories_t1_14_9": 0, "packaged_accessories_t1_14_10": 0, "packaged_accessories_t1_14_11": 0, "packaged_accessories_t1_14_12": 0, "packaged_accessories_t1_14_13": 0, "packaged_accessories_t1_14_14": 0, "packaged_accessories_t1_14_15": 0, "packaged_accessories_t1_14_16": 0, "packaged_accessories_t1_14_17": 0, "packaged_accessories_t1_14_18": 0, "packaged_accessories_t1_14_19": 0, "packaged_accessories_t1_13_0": 0, "packaged_accessories_t1_13_1": 0, "packaged_accessories_t1_13_2": 0, "packaged_accessories_t1_13_3": 0, "packaged_accessories_t1_13_4": 0, "packaged_accessories_t1_13_5": 0, "packaged_accessories_t1_13_6": 0, "packaged_accessories_t1_13_7": 0, "packaged_accessories_t1_13_8": 0, "packaged_accessories_t1_13_9": 0, "packaged_accessories_t1_13_10": 0, "packaged_accessories_t1_13_11": 0, "packaged_accessories_t1_13_12": 0, "packaged_accessories_t1_13_13": 0, "packaged_accessories_t1_13_14": 0, "packaged_accessories_t1_13_15": 0, "packaged_accessories_t1_13_16": 0, "packaged_accessories_t1_13_17": 0, "packaged_accessories_t1_13_18": 0, "packaged_accessories_t1_13_19": 0, "packaged_accessories_t1_12_0": 0, "packaged_accessories_t1_12_1": 0, "packaged_accessories_t1_12_2": 0, "packaged_accessories_t1_12_3": 0, "packaged_accessories_t1_12_4": 0, "packaged_accessories_t1_12_5": 0, "packaged_accessories_t1_12_6": 0, "packaged_accessories_t1_12_7": 0, "packaged_accessories_t1_12_8": 0, "packaged_accessories_t1_12_9": 0, "packaged_accessories_t1_12_10": 0, "packaged_accessories_t1_12_11": 0, "packaged_accessories_t1_12_12": 0, "packaged_accessories_t1_12_13": 0, "packaged_accessories_t1_12_14": 0, "packaged_accessories_t1_12_15": 0, "packaged_accessories_t1_12_16": 0, "packaged_accessories_t1_12_17": 0, "packaged_accessories_t1_12_18": 0, "packaged_accessories_t1_12_19": 0, "packaged_accessories_t1_10_0": 0, "packaged_accessories_t1_10_1": 0, "packaged_accessories_t1_10_2": 0, "packaged_accessories_t1_10_3": 0, "packaged_accessories_t1_10_4": 0, "packaged_accessories_t1_10_5": 0, "packaged_accessories_t1_10_6": 0, "packaged_accessories_t1_10_7": 0, "packaged_accessories_t1_10_8": 0, "packaged_accessories_t1_10_9": 0, "packaged_accessories_t1_10_10": 0, "packaged_accessories_t1_10_11": 0, "packaged_accessories_t1_10_12": 0, "packaged_accessories_t1_10_13": 0, "packaged_accessories_t1_10_14": 0, "packaged_accessories_t1_10_15": 0, "packaged_accessories_t1_10_16": 0, "packaged_accessories_t1_10_17": 0, "packaged_accessories_t1_10_18": 0, "packaged_accessories_t1_10_19": 0, "packaged_accessories_t1_11_0": 0, "packaged_accessories_t1_11_1": 0, "packaged_accessories_t1_11_2": 0, "packaged_accessories_t1_11_3": 0, "packaged_accessories_t1_11_4": 0, "packaged_accessories_t1_11_5": 0, "packaged_accessories_t1_11_6": 0, "packaged_accessories_t1_11_7": 0, "packaged_accessories_t1_11_8": 0, "packaged_accessories_t1_11_9": 0, "packaged_accessories_t1_11_10": 0, "packaged_accessories_t1_11_11": 0, "packaged_accessories_t1_11_12": 0, "packaged_accessories_t1_11_13": 0, "packaged_accessories_t1_11_14": 0, "packaged_accessories_t1_11_15": 0, "packaged_accessories_t1_11_16": 0, "packaged_accessories_t1_11_17": 0, "packaged_accessories_t1_11_18": 0, "packaged_accessories_t1_11_19": 0, "packaged_accessories_t1_1_0": 0, "packaged_accessories_t1_1_1": 0, "packaged_accessories_t1_1_2": 0, "packaged_accessories_t1_1_3": 0, "packaged_accessories_t1_1_4": 0, "packaged_accessories_t1_1_5": 0, "packaged_accessories_t1_1_6": 0, "packaged_accessories_t1_1_7": 0, "packaged_accessories_t1_1_8": 0, "packaged_accessories_t1_1_9": 0, "packaged_accessories_t1_1_10": 0, "packaged_accessories_t1_1_11": 0, "packaged_accessories_t1_1_12": 0, "packaged_accessories_t1_1_13": 0, "packaged_accessories_t1_1_14": 0, "packaged_accessories_t1_1_15": 0, "packaged_accessories_t1_1_16": 0, "packaged_accessories_t1_1_17": 0, "packaged_accessories_t1_1_18": 0, "packaged_accessories_t1_1_19": 0, "packaged_accessories_t1_2_0": 0, "packaged_accessories_t1_2_1": 0, "packaged_accessories_t1_2_2": 0, "packaged_accessories_t1_2_3": 0, "packaged_accessories_t1_2_4": 0, "packaged_accessories_t1_2_5": 0, "packaged_accessories_t1_2_6": 0, "packaged_accessories_t1_2_7": 0, "packaged_accessories_t1_2_8": 0, "packaged_accessories_t1_2_9": 0, "packaged_accessories_t1_2_10": 0, "packaged_accessories_t1_2_11": 0, "packaged_accessories_t1_2_12": 0, "packaged_accessories_t1_2_13": 0, "packaged_accessories_t1_2_14": 0, "packaged_accessories_t1_2_15": 0, "packaged_accessories_t1_2_16": 0, "packaged_accessories_t1_2_17": 0, "packaged_accessories_t1_2_18": 0, "packaged_accessories_t1_2_19": 0, "packaged_accessories_t1_3_0": 0, "packaged_accessories_t1_3_1": 0, "packaged_accessories_t1_3_2": 0, "packaged_accessories_t1_3_3": 0, "packaged_accessories_t1_3_4": 0, "packaged_accessories_t1_3_5": 0, "packaged_accessories_t1_3_6": 0, "packaged_accessories_t1_3_7": 0, "packaged_accessories_t1_3_8": 0, "packaged_accessories_t1_3_9": 0, "packaged_accessories_t1_3_10": 0, "packaged_accessories_t1_3_11": 0, "packaged_accessories_t1_3_12": 0, "packaged_accessories_t1_3_13": 0, "packaged_accessories_t1_3_14": 0, "packaged_accessories_t1_3_15": 0, "packaged_accessories_t1_3_16": 0, "packaged_accessories_t1_3_17": 0, "packaged_accessories_t1_3_18": 0, "packaged_accessories_t1_3_19": 0, "packaged_accessories_t1_7_0": 0, "packaged_accessories_t1_7_1": 0, "packaged_accessories_t1_7_2": 0, "packaged_accessories_t1_7_3": 0, "packaged_accessories_t1_7_4": 0, "packaged_accessories_t1_7_5": 0, "packaged_accessories_t1_7_6": 0, "packaged_accessories_t1_7_7": 0, "packaged_accessories_t1_7_8": 0, "packaged_accessories_t1_7_9": 0, "packaged_accessories_t1_7_10": 0, "packaged_accessories_t1_7_11": 0, "packaged_accessories_t1_7_12": 0, "packaged_accessories_t1_7_13": 0, "packaged_accessories_t1_7_14": 0, "packaged_accessories_t1_7_15": 0, "packaged_accessories_t1_7_16": 0, "packaged_accessories_t1_7_17": 0, "packaged_accessories_t1_7_18": 0, "packaged_accessories_t1_7_19": 0, "packaged_accessories_t1_6_0": 0, "packaged_accessories_t1_6_1": 0, "packaged_accessories_t1_6_2": 0, "packaged_accessories_t1_6_3": 0, "packaged_accessories_t1_6_4": 0, "packaged_accessories_t1_6_5": 0, "packaged_accessories_t1_6_6": 0, "packaged_accessories_t1_6_7": 0, "packaged_accessories_t1_6_8": 0, "packaged_accessories_t1_6_9": 0, "packaged_accessories_t1_6_10": 0, "packaged_accessories_t1_6_11": 0, "packaged_accessories_t1_6_12": 0, "packaged_accessories_t1_6_13": 0, "packaged_accessories_t1_6_14": 0, "packaged_accessories_t1_6_15": 0, "packaged_accessories_t1_6_16": 0, "packaged_accessories_t1_6_17": 0, "packaged_accessories_t1_6_18": 0, "packaged_accessories_t1_6_19": 0, "packaged_accessories_t1_4_0": 0, "packaged_accessories_t1_4_1": 0, "packaged_accessories_t1_4_2": 0, "packaged_accessories_t1_4_3": 0, "packaged_accessories_t1_4_4": 0, "packaged_accessories_t1_4_5": 0, "packaged_accessories_t1_4_6": 0, "packaged_accessories_t1_4_7": 0, "packaged_accessories_t1_4_8": 0, "packaged_accessories_t1_4_9": 0, "packaged_accessories_t1_4_10": 0, "packaged_accessories_t1_4_11": 0, "packaged_accessories_t1_4_12": 0, "packaged_accessories_t1_4_13": 0, "packaged_accessories_t1_4_14": 0, "packaged_accessories_t1_4_15": 0, "packaged_accessories_t1_4_16": 0, "packaged_accessories_t1_4_17": 0, "packaged_accessories_t1_4_18": 0, "packaged_accessories_t1_4_19": 0, "packaged_accessories_t1_5_0": 0, "packaged_accessories_t1_5_1": 0, "packaged_accessories_t1_5_2": 0, "packaged_accessories_t1_5_3": 0, "packaged_accessories_t1_5_4": 0, "packaged_accessories_t1_5_5": 0, "packaged_accessories_t1_5_6": 0, "packaged_accessories_t1_5_7": 0, "packaged_accessories_t1_5_8": 0, "packaged_accessories_t1_5_9": 0, "packaged_accessories_t1_5_10": 0, "packaged_accessories_t1_5_11": 0, "packaged_accessories_t1_5_12": 0, "packaged_accessories_t1_5_13": 0, "packaged_accessories_t1_5_14": 0, "packaged_accessories_t1_5_15": 0, "packaged_accessories_t1_5_16": 0, "packaged_accessories_t1_5_17": 0, "packaged_accessories_t1_5_18": 0, "packaged_accessories_t1_5_19": 0, "landmarks_t1_8_0": 1, "landmarks_t1_8_1": 1, "landmarks_t1_8_2": 1, "landmarks_t1_8_3": 1, "landmarks_t1_8_4": 1, "landmarks_t1_8_5": 1, "landmarks_t1_8_6": 1, "landmarks_t1_8_7": 1, "landmarks_t1_8_8": 1, "landmarks_t1_8_9": 1, "landmarks_t1_8_10": 1, "landmarks_t1_8_11": 1, "landmarks_t1_8_12": 1, "landmarks_t1_8_13": 1, "landmarks_t1_8_14": 1, "landmarks_t1_8_15": 1, "landmarks_t1_8_16": 1, "landmarks_t1_8_17": 1, "landmarks_t1_8_18": 1, "landmarks_t1_8_19": 1, "landmarks_t1_9_0": 1, "landmarks_t1_9_1": 1, "landmarks_t1_9_2": 1, "landmarks_t1_9_3": 1, "landmarks_t1_9_4": 1, "landmarks_t1_9_5": 1, "landmarks_t1_9_6": 1, "landmarks_t1_9_7": 1, "landmarks_t1_9_8": 1, "landmarks_t1_9_9": 1, "landmarks_t1_9_10": 1, "landmarks_t1_9_11": 1, "landmarks_t1_9_12": 1, "landmarks_t1_9_13": 1, "landmarks_t1_9_14": 1, "landmarks_t1_9_15": 1, "landmarks_t1_9_16": 1, "landmarks_t1_9_17": 1, "landmarks_t1_9_18": 1, "landmarks_t1_9_19": 1, "landmarks_t1_13_0": 1, "landmarks_t1_13_1": 1, "landmarks_t1_13_2": 1, "landmarks_t1_13_3": 1, "landmarks_t1_13_4": 1, "landmarks_t1_13_5": 1, "landmarks_t1_13_6": 1, "landmarks_t1_13_7": 1, "landmarks_t1_13_8": 1, "landmarks_t1_13_9": 1, "landmarks_t1_13_10": 1, "landmarks_t1_13_11": 1, "landmarks_t1_13_12": 1, "landmarks_t1_13_13": 1, "landmarks_t1_13_14": 1, "landmarks_t1_13_15": 1, "landmarks_t1_13_16": 1, "landmarks_t1_13_17": 1, "landmarks_t1_13_18": 1, "landmarks_t1_13_19": 1, "landmarks_t1_12_0": 1, "landmarks_t1_12_1": 1, "landmarks_t1_12_2": 1, "landmarks_t1_12_3": 1, "landmarks_t1_12_4": 1, "landmarks_t1_12_5": 1, "landmarks_t1_12_6": 1, "landmarks_t1_12_7": 1, "landmarks_t1_12_8": 1, "landmarks_t1_12_9": 1, "landmarks_t1_12_10": 1, "landmarks_t1_12_11": 1, "landmarks_t1_12_12": 1, "landmarks_t1_12_13": 1, "landmarks_t1_12_14": 1, "landmarks_t1_12_15": 1, "landmarks_t1_12_16": 1, "landmarks_t1_12_17": 1, "landmarks_t1_12_18": 1, "landmarks_t1_12_19": 1, "landmarks_t1_10_0": 1, "landmarks_t1_10_1": 1, "landmarks_t1_10_2": 1, "landmarks_t1_10_3": 1, "landmarks_t1_10_4": 1, "landmarks_t1_10_5": 1, "landmarks_t1_10_6": 1, "landmarks_t1_10_7": 1, "landmarks_t1_10_8": 1, "landmarks_t1_10_9": 1, "landmarks_t1_10_10": 1, "landmarks_t1_10_11": 1, "landmarks_t1_10_12": 1, "landmarks_t1_10_13": 1, "landmarks_t1_10_14": 1, "landmarks_t1_10_15": 1, "landmarks_t1_10_16": 1, "landmarks_t1_10_17": 1, "landmarks_t1_10_18": 1, "landmarks_t1_10_19": 1, "landmarks_t1_11_0": 1, "landmarks_t1_11_1": 1, "landmarks_t1_11_2": 1, "landmarks_t1_11_3": 1, "landmarks_t1_11_4": 1, "landmarks_t1_11_5": 1, "landmarks_t1_11_6": 1, "landmarks_t1_11_7": 1, "landmarks_t1_11_8": 1, "landmarks_t1_11_9": 1, "landmarks_t1_11_10": 1, "landmarks_t1_11_11": 1, "landmarks_t1_11_12": 1, "landmarks_t1_11_13": 1, "landmarks_t1_11_14": 1, "landmarks_t1_11_15": 1, "landmarks_t1_11_16": 1, "landmarks_t1_11_17": 1, "landmarks_t1_11_18": 1, "landmarks_t1_11_19": 1, "landmarks_t1_1_0": 1, "landmarks_t1_1_1": 1, "landmarks_t1_1_2": 1, "landmarks_t1_1_3": 1, "landmarks_t1_1_4": 1, "landmarks_t1_1_5": 1, "landmarks_t1_1_6": 1, "landmarks_t1_1_7": 1, "landmarks_t1_1_8": 1, "landmarks_t1_1_9": 1, "landmarks_t1_1_10": 1, "landmarks_t1_1_11": 1, "landmarks_t1_1_12": 1, "landmarks_t1_1_13": 1, "landmarks_t1_1_14": 1, "landmarks_t1_1_15": 1, "landmarks_t1_1_16": 1, "landmarks_t1_1_17": 1, "landmarks_t1_1_18": 1, "landmarks_t1_1_19": 1, "landmarks_t1_2_0": 1, "landmarks_t1_2_1": 1, "landmarks_t1_2_2": 1, "landmarks_t1_2_3": 1, "landmarks_t1_2_4": 1, "landmarks_t1_2_5": 1, "landmarks_t1_2_6": 1, "landmarks_t1_2_7": 1, "landmarks_t1_2_8": 1, "landmarks_t1_2_9": 1, "landmarks_t1_2_10": 1, "landmarks_t1_2_11": 1, "landmarks_t1_2_12": 1, "landmarks_t1_2_13": 1, "landmarks_t1_2_14": 1, "landmarks_t1_2_15": 1, "landmarks_t1_2_16": 1, "landmarks_t1_2_17": 1, "landmarks_t1_2_18": 1, "landmarks_t1_2_19": 1, "landmarks_t1_3_0": 1, "landmarks_t1_3_1": 1, "landmarks_t1_3_2": 1, "landmarks_t1_3_3": 1, "landmarks_t1_3_4": 1, "landmarks_t1_3_5": 1, "landmarks_t1_3_6": 1, "landmarks_t1_3_7": 1, "landmarks_t1_3_8": 1, "landmarks_t1_3_9": 1, "landmarks_t1_3_10": 1, "landmarks_t1_3_11": 1, "landmarks_t1_3_12": 1, "landmarks_t1_3_13": 1, "landmarks_t1_3_14": 1, "landmarks_t1_3_15": 1, "landmarks_t1_3_16": 1, "landmarks_t1_3_17": 1, "landmarks_t1_3_18": 1, "landmarks_t1_3_19": 1, "landmarks_t1_7_0": 1, "landmarks_t1_7_1": 1, "landmarks_t1_7_2": 1, "landmarks_t1_7_3": 1, "landmarks_t1_7_4": 1, "landmarks_t1_7_5": 1, "landmarks_t1_7_6": 1, "landmarks_t1_7_7": 1, "landmarks_t1_7_8": 1, "landmarks_t1_7_9": 1, "landmarks_t1_7_10": 1, "landmarks_t1_7_11": 1, "landmarks_t1_7_12": 1, "landmarks_t1_7_13": 1, "landmarks_t1_7_14": 1, "landmarks_t1_7_15": 1, "landmarks_t1_7_16": 1, "landmarks_t1_7_17": 1, "landmarks_t1_7_18": 1, "landmarks_t1_7_19": 1, "landmarks_t1_6_0": 1, "landmarks_t1_6_1": 1, "landmarks_t1_6_2": 1, "landmarks_t1_6_3": 1, "landmarks_t1_6_4": 1, "landmarks_t1_6_5": 1, "landmarks_t1_6_6": 1, "landmarks_t1_6_7": 1, "landmarks_t1_6_8": 1, "landmarks_t1_6_9": 1, "landmarks_t1_6_10": 1, "landmarks_t1_6_11": 1, "landmarks_t1_6_12": 1, "landmarks_t1_6_13": 1, "landmarks_t1_6_14": 1, "landmarks_t1_6_15": 1, "landmarks_t1_6_16": 1, "landmarks_t1_6_17": 1, "landmarks_t1_6_18": 1, "landmarks_t1_6_19": 1, "landmarks_t1_4_0": 1, "landmarks_t1_4_1": 1, "landmarks_t1_4_2": 1, "landmarks_t1_4_3": 1, "landmarks_t1_4_4": 1, "landmarks_t1_4_5": 1, "landmarks_t1_4_6": 1, "landmarks_t1_4_7": 1, "landmarks_t1_4_8": 1, "landmarks_t1_4_9": 1, "landmarks_t1_4_10": 1, "landmarks_t1_4_11": 1, "landmarks_t1_4_12": 1, "landmarks_t1_4_13": 1, "landmarks_t1_4_14": 1, "landmarks_t1_4_15": 1, "landmarks_t1_4_16": 1, "landmarks_t1_4_17": 1, "landmarks_t1_4_18": 1, "landmarks_t1_4_19": 1, "landmarks_t1_5_0": 1, "landmarks_t1_5_1": 1, "landmarks_t1_5_2": 1, "landmarks_t1_5_3": 1, "landmarks_t1_5_4": 1, "landmarks_t1_5_5": 1, "landmarks_t1_5_6": 1, "landmarks_t1_5_7": 1, "landmarks_t1_5_8": 1, "landmarks_t1_5_9": 1, "landmarks_t1_5_10": 1, "landmarks_t1_5_11": 1, "landmarks_t1_5_12": 1, "landmarks_t1_5_13": 1, "landmarks_t1_5_14": 1, "landmarks_t1_5_15": 1, "landmarks_t1_5_16": 1, "landmarks_t1_5_17": 1, "landmarks_t1_5_18": 1, "landmarks_t1_5_19": 1, "packaged_accessories_t2_12_0": 2, "packaged_accessories_t2_12_1": 2, "packaged_accessories_t2_12_2": 2, "packaged_accessories_t2_12_3": 2, "packaged_accessories_t2_12_4": 2, "packaged_accessories_t2_12_5": 2, "packaged_accessories_t2_12_6": 2, "packaged_accessories_t2_12_7": 2, "packaged_accessories_t2_12_8": 2, "packaged_accessories_t2_12_9": 2, "packaged_accessories_t2_12_10": 2, "packaged_accessories_t2_12_11": 2, "packaged_accessories_t2_12_12": 2, "packaged_accessories_t2_12_13": 2, "packaged_accessories_t2_12_14": 2, "packaged_accessories_t2_12_15": 2, "packaged_accessories_t2_12_16": 2, "packaged_accessories_t2_12_17": 2, "packaged_accessories_t2_12_18": 2, "packaged_accessories_t2_12_19": 2, "packaged_accessories_t2_11_0": 2, "packaged_accessories_t2_11_1": 2, "packaged_accessories_t2_11_2": 2, "packaged_accessories_t2_11_3": 2, "packaged_accessories_t2_11_4": 2, "packaged_accessories_t2_11_5": 2, "packaged_accessories_t2_11_6": 2, "packaged_accessories_t2_11_7": 2, "packaged_accessories_t2_11_8": 2, "packaged_accessories_t2_11_9": 2, "packaged_accessories_t2_11_10": 2, "packaged_accessories_t2_11_11": 2, "packaged_accessories_t2_11_12": 2, "packaged_accessories_t2_11_13": 2, "packaged_accessories_t2_11_14": 2, "packaged_accessories_t2_11_15": 2, "packaged_accessories_t2_11_16": 2, "packaged_accessories_t2_11_17": 2, "packaged_accessories_t2_11_18": 2, "packaged_accessories_t2_11_19": 2, "packaged_accessories_t2_10_0": 2, "packaged_accessories_t2_10_1": 2, "packaged_accessories_t2_10_2": 2, "packaged_accessories_t2_10_3": 2, "packaged_accessories_t2_10_4": 2, "packaged_accessories_t2_10_5": 2, "packaged_accessories_t2_10_6": 2, "packaged_accessories_t2_10_7": 2, "packaged_accessories_t2_10_8": 2, "packaged_accessories_t2_10_9": 2, "packaged_accessories_t2_10_10": 2, "packaged_accessories_t2_10_11": 2, "packaged_accessories_t2_10_12": 2, "packaged_accessories_t2_10_13": 2, "packaged_accessories_t2_10_14": 2, "packaged_accessories_t2_10_15": 2, "packaged_accessories_t2_10_16": 2, "packaged_accessories_t2_10_17": 2, "packaged_accessories_t2_10_18": 2, "packaged_accessories_t2_10_19": 2, "packaged_accessories_t2_9_0": 2, "packaged_accessories_t2_9_1": 2, "packaged_accessories_t2_9_2": 2, "packaged_accessories_t2_9_3": 2, "packaged_accessories_t2_9_4": 2, "packaged_accessories_t2_9_5": 2, "packaged_accessories_t2_9_6": 2, "packaged_accessories_t2_9_7": 2, "packaged_accessories_t2_9_8": 2, "packaged_accessories_t2_9_9": 2, "packaged_accessories_t2_9_10": 2, "packaged_accessories_t2_9_11": 2, "packaged_accessories_t2_9_12": 2, "packaged_accessories_t2_9_13": 2, "packaged_accessories_t2_9_14": 2, "packaged_accessories_t2_9_15": 2, "packaged_accessories_t2_9_16": 2, "packaged_accessories_t2_9_17": 2, "packaged_accessories_t2_9_18": 2, "packaged_accessories_t2_9_19": 2, "packaged_accessories_t2_8_0": 2, "packaged_accessories_t2_8_1": 2, "packaged_accessories_t2_8_2": 2, "packaged_accessories_t2_8_3": 2, "packaged_accessories_t2_8_4": 2, "packaged_accessories_t2_8_5": 2, "packaged_accessories_t2_8_6": 2, "packaged_accessories_t2_8_7": 2, "packaged_accessories_t2_8_8": 2, "packaged_accessories_t2_8_9": 2, "packaged_accessories_t2_8_10": 2, "packaged_accessories_t2_8_11": 2, "packaged_accessories_t2_8_12": 2, "packaged_accessories_t2_8_13": 2, "packaged_accessories_t2_8_14": 2, "packaged_accessories_t2_8_15": 2, "packaged_accessories_t2_8_16": 2, "packaged_accessories_t2_8_17": 2, "packaged_accessories_t2_8_18": 2, "packaged_accessories_t2_8_19": 2, "packaged_accessories_t2_1_0": 2, "packaged_accessories_t2_1_1": 2, "packaged_accessories_t2_1_2": 2, "packaged_accessories_t2_1_3": 2, "packaged_accessories_t2_1_4": 2, "packaged_accessories_t2_1_5": 2, "packaged_accessories_t2_1_6": 2, "packaged_accessories_t2_1_7": 2, "packaged_accessories_t2_1_8": 2, "packaged_accessories_t2_1_9": 2, "packaged_accessories_t2_1_10": 2, "packaged_accessories_t2_1_11": 2, "packaged_accessories_t2_1_12": 2, "packaged_accessories_t2_1_13": 2, "packaged_accessories_t2_1_14": 2, "packaged_accessories_t2_1_15": 2, "packaged_accessories_t2_1_16": 2, "packaged_accessories_t2_1_17": 2, "packaged_accessories_t2_1_18": 2, "packaged_accessories_t2_1_19": 2, "packaged_accessories_t2_3_0": 2, "packaged_accessories_t2_3_1": 2, "packaged_accessories_t2_3_2": 2, "packaged_accessories_t2_3_3": 2, "packaged_accessories_t2_3_4": 2, "packaged_accessories_t2_3_5": 2, "packaged_accessories_t2_3_6": 2, "packaged_accessories_t2_3_7": 2, "packaged_accessories_t2_3_8": 2, "packaged_accessories_t2_3_9": 2, "packaged_accessories_t2_3_10": 2, "packaged_accessories_t2_3_11": 2, "packaged_accessories_t2_3_12": 2, "packaged_accessories_t2_3_13": 2, "packaged_accessories_t2_3_14": 2, "packaged_accessories_t2_3_15": 2, "packaged_accessories_t2_3_16": 2, "packaged_accessories_t2_3_17": 2, "packaged_accessories_t2_3_18": 2, "packaged_accessories_t2_3_19": 2, "packaged_accessories_t2_2_0": 2, "packaged_accessories_t2_2_1": 2, "packaged_accessories_t2_2_2": 2, "packaged_accessories_t2_2_3": 2, "packaged_accessories_t2_2_4": 2, "packaged_accessories_t2_2_5": 2, "packaged_accessories_t2_2_6": 2, "packaged_accessories_t2_2_7": 2, "packaged_accessories_t2_2_8": 2, "packaged_accessories_t2_2_9": 2, "packaged_accessories_t2_2_10": 2, "packaged_accessories_t2_2_11": 2, "packaged_accessories_t2_2_12": 2, "packaged_accessories_t2_2_13": 2, "packaged_accessories_t2_2_14": 2, "packaged_accessories_t2_2_15": 2, "packaged_accessories_t2_2_16": 2, "packaged_accessories_t2_2_17": 2, "packaged_accessories_t2_2_18": 2, "packaged_accessories_t2_2_19": 2, "packaged_accessories_t2_6_0": 2, "packaged_accessories_t2_6_1": 2, "packaged_accessories_t2_6_2": 2, "packaged_accessories_t2_6_3": 2, "packaged_accessories_t2_6_4": 2, "packaged_accessories_t2_6_5": 2, "packaged_accessories_t2_6_6": 2, "packaged_accessories_t2_6_7": 2, "packaged_accessories_t2_6_8": 2, "packaged_accessories_t2_6_9": 2, "packaged_accessories_t2_6_10": 2, "packaged_accessories_t2_6_11": 2, "packaged_accessories_t2_6_12": 2, "packaged_accessories_t2_6_13": 2, "packaged_accessories_t2_6_14": 2, "packaged_accessories_t2_6_15": 2, "packaged_accessories_t2_6_16": 2, "packaged_accessories_t2_6_17": 2, "packaged_accessories_t2_6_18": 2, "packaged_accessories_t2_6_19": 2, "packaged_accessories_t2_7_0": 2, "packaged_accessories_t2_7_1": 2, "packaged_accessories_t2_7_2": 2, "packaged_accessories_t2_7_3": 2, "packaged_accessories_t2_7_4": 2, "packaged_accessories_t2_7_5": 2, "packaged_accessories_t2_7_6": 2, "packaged_accessories_t2_7_7": 2, "packaged_accessories_t2_7_8": 2, "packaged_accessories_t2_7_9": 2, "packaged_accessories_t2_7_10": 2, "packaged_accessories_t2_7_11": 2, "packaged_accessories_t2_7_12": 2, "packaged_accessories_t2_7_13": 2, "packaged_accessories_t2_7_14": 2, "packaged_accessories_t2_7_15": 2, "packaged_accessories_t2_7_16": 2, "packaged_accessories_t2_7_17": 2, "packaged_accessories_t2_7_18": 2, "packaged_accessories_t2_7_19": 2, "packaged_accessories_t2_5_0": 2, "packaged_accessories_t2_5_1": 2, "packaged_accessories_t2_5_2": 2, "packaged_accessories_t2_5_3": 2, "packaged_accessories_t2_5_4": 2, "packaged_accessories_t2_5_5": 2, "packaged_accessories_t2_5_6": 2, "packaged_accessories_t2_5_7": 2, "packaged_accessories_t2_5_8": 2, "packaged_accessories_t2_5_9": 2, "packaged_accessories_t2_5_10": 2, "packaged_accessories_t2_5_11": 2, "packaged_accessories_t2_5_12": 2, "packaged_accessories_t2_5_13": 2, "packaged_accessories_t2_5_14": 2, "packaged_accessories_t2_5_15": 2, "packaged_accessories_t2_5_16": 2, "packaged_accessories_t2_5_17": 2, "packaged_accessories_t2_5_18": 2, "packaged_accessories_t2_5_19": 2, "packaged_accessories_t2_4_0": 2, "packaged_accessories_t2_4_1": 2, "packaged_accessories_t2_4_2": 2, "packaged_accessories_t2_4_3": 2, "packaged_accessories_t2_4_4": 2, "packaged_accessories_t2_4_5": 2, "packaged_accessories_t2_4_6": 2, "packaged_accessories_t2_4_7": 2, "packaged_accessories_t2_4_8": 2, "packaged_accessories_t2_4_9": 2, "packaged_accessories_t2_4_10": 2, "packaged_accessories_t2_4_11": 2, "packaged_accessories_t2_4_12": 2, "packaged_accessories_t2_4_13": 2, "packaged_accessories_t2_4_14": 2, "packaged_accessories_t2_4_15": 2, "packaged_accessories_t2_4_16": 2, "packaged_accessories_t2_4_17": 2, "packaged_accessories_t2_4_18": 2, "packaged_accessories_t2_4_19": 2, "dishes_t1_8_0": 3, "dishes_t1_8_1": 3, "dishes_t1_8_2": 3, "dishes_t1_8_3": 3, "dishes_t1_8_4": 3, "dishes_t1_8_5": 3, "dishes_t1_8_6": 3, "dishes_t1_8_7": 3, "dishes_t1_8_8": 3, "dishes_t1_8_9": 3, "dishes_t1_8_10": 3, "dishes_t1_8_11": 3, "dishes_t1_8_12": 3, "dishes_t1_8_13": 3, "dishes_t1_8_14": 3, "dishes_t1_8_15": 3, "dishes_t1_8_16": 3, "dishes_t1_8_17": 3, "dishes_t1_8_18": 3, "dishes_t1_8_19": 3, "dishes_t1_9_0": 3, "dishes_t1_9_1": 3, "dishes_t1_9_2": 3, "dishes_t1_9_3": 3, "dishes_t1_9_4": 3, "dishes_t1_9_5": 3, "dishes_t1_9_6": 3, "dishes_t1_9_7": 3, "dishes_t1_9_8": 3, "dishes_t1_9_9": 3, "dishes_t1_9_10": 3, "dishes_t1_9_11": 3, "dishes_t1_9_12": 3, "dishes_t1_9_13": 3, "dishes_t1_9_14": 3, "dishes_t1_9_15": 3, "dishes_t1_9_16": 3, "dishes_t1_9_17": 3, "dishes_t1_9_18": 3, "dishes_t1_9_19": 3, "dishes_t1_10_0": 3, "dishes_t1_10_1": 3, "dishes_t1_10_2": 3, "dishes_t1_10_3": 3, "dishes_t1_10_4": 3, "dishes_t1_10_5": 3, "dishes_t1_10_6": 3, "dishes_t1_10_7": 3, "dishes_t1_10_8": 3, "dishes_t1_10_9": 3, "dishes_t1_10_10": 3, "dishes_t1_10_11": 3, "dishes_t1_10_12": 3, "dishes_t1_10_13": 3, "dishes_t1_10_14": 3, "dishes_t1_10_15": 3, "dishes_t1_10_16": 3, "dishes_t1_10_17": 3, "dishes_t1_10_18": 3, "dishes_t1_10_19": 3, "dishes_t1_11_0": 3, "dishes_t1_11_1": 3, "dishes_t1_11_2": 3, "dishes_t1_11_3": 3, "dishes_t1_11_4": 3, "dishes_t1_11_5": 3, "dishes_t1_11_6": 3, "dishes_t1_11_7": 3, "dishes_t1_11_8": 3, "dishes_t1_11_9": 3, "dishes_t1_11_10": 3, "dishes_t1_11_11": 3, "dishes_t1_11_12": 3, "dishes_t1_11_13": 3, "dishes_t1_11_14": 3, "dishes_t1_11_15": 3, "dishes_t1_11_16": 3, "dishes_t1_11_17": 3, "dishes_t1_11_18": 3, "dishes_t1_11_19": 3, "dishes_t1_1_0": 3, "dishes_t1_1_1": 3, "dishes_t1_1_2": 3, "dishes_t1_1_3": 3, "dishes_t1_1_4": 3, "dishes_t1_1_5": 3, "dishes_t1_1_6": 3, "dishes_t1_1_7": 3, "dishes_t1_1_8": 3, "dishes_t1_1_9": 3, "dishes_t1_1_10": 3, "dishes_t1_1_11": 3, "dishes_t1_1_12": 3, "dishes_t1_1_13": 3, "dishes_t1_1_14": 3, "dishes_t1_1_15": 3, "dishes_t1_1_16": 3, "dishes_t1_1_17": 3, "dishes_t1_1_18": 3, "dishes_t1_1_19": 3, "dishes_t1_2_0": 3, "dishes_t1_2_1": 3, "dishes_t1_2_2": 3, "dishes_t1_2_3": 3, "dishes_t1_2_4": 3, "dishes_t1_2_5": 3, "dishes_t1_2_6": 3, "dishes_t1_2_7": 3, "dishes_t1_2_8": 3, "dishes_t1_2_9": 3, "dishes_t1_2_10": 3, "dishes_t1_2_11": 3, "dishes_t1_2_12": 3, "dishes_t1_2_13": 3, "dishes_t1_2_14": 3, "dishes_t1_2_15": 3, "dishes_t1_2_16": 3, "dishes_t1_2_17": 3, "dishes_t1_2_18": 3, "dishes_t1_2_19": 3, "dishes_t1_3_0": 3, "dishes_t1_3_1": 3, "dishes_t1_3_2": 3, "dishes_t1_3_3": 3, "dishes_t1_3_4": 3, "dishes_t1_3_5": 3, "dishes_t1_3_6": 3, "dishes_t1_3_7": 3, "dishes_t1_3_8": 3, "dishes_t1_3_9": 3, "dishes_t1_3_10": 3, "dishes_t1_3_11": 3, "dishes_t1_3_12": 3, "dishes_t1_3_13": 3, "dishes_t1_3_14": 3, "dishes_t1_3_15": 3, "dishes_t1_3_16": 3, "dishes_t1_3_17": 3, "dishes_t1_3_18": 3, "dishes_t1_3_19": 3, "dishes_t1_7_0": 3, "dishes_t1_7_1": 3, "dishes_t1_7_2": 3, "dishes_t1_7_3": 3, "dishes_t1_7_4": 3, "dishes_t1_7_5": 3, "dishes_t1_7_6": 3, "dishes_t1_7_7": 3, "dishes_t1_7_8": 3, "dishes_t1_7_9": 3, "dishes_t1_7_10": 3, "dishes_t1_7_11": 3, "dishes_t1_7_12": 3, "dishes_t1_7_13": 3, "dishes_t1_7_14": 3, "dishes_t1_7_15": 3, "dishes_t1_7_16": 3, "dishes_t1_7_17": 3, "dishes_t1_7_18": 3, "dishes_t1_7_19": 3, "dishes_t1_6_0": 3, "dishes_t1_6_1": 3, "dishes_t1_6_2": 3, "dishes_t1_6_3": 3, "dishes_t1_6_4": 3, "dishes_t1_6_5": 3, "dishes_t1_6_6": 3, "dishes_t1_6_7": 3, "dishes_t1_6_8": 3, "dishes_t1_6_9": 3, "dishes_t1_6_10": 3, "dishes_t1_6_11": 3, "dishes_t1_6_12": 3, "dishes_t1_6_13": 3, "dishes_t1_6_14": 3, "dishes_t1_6_15": 3, "dishes_t1_6_16": 3, "dishes_t1_6_17": 3, "dishes_t1_6_18": 3, "dishes_t1_6_19": 3, "dishes_t1_4_0": 3, "dishes_t1_4_1": 3, "dishes_t1_4_2": 3, "dishes_t1_4_3": 3, "dishes_t1_4_4": 3, "dishes_t1_4_5": 3, "dishes_t1_4_6": 3, "dishes_t1_4_7": 3, "dishes_t1_4_8": 3, "dishes_t1_4_9": 3, "dishes_t1_4_10": 3, "dishes_t1_4_11": 3, "dishes_t1_4_12": 3, "dishes_t1_4_13": 3, "dishes_t1_4_14": 3, "dishes_t1_4_15": 3, "dishes_t1_4_16": 3, "dishes_t1_4_17": 3, "dishes_t1_4_18": 3, "dishes_t1_4_19": 3, "dishes_t1_5_0": 3, "dishes_t1_5_1": 3, "dishes_t1_5_2": 3, "dishes_t1_5_3": 3, "dishes_t1_5_4": 3, "dishes_t1_5_5": 3, "dishes_t1_5_6": 3, "dishes_t1_5_7": 3, "dishes_t1_5_8": 3, "dishes_t1_5_9": 3, "dishes_t1_5_10": 3, "dishes_t1_5_11": 3, "dishes_t1_5_12": 3, "dishes_t1_5_13": 3, "dishes_t1_5_14": 3, "dishes_t1_5_15": 3, "dishes_t1_5_16": 3, "dishes_t1_5_17": 3, "dishes_t1_5_18": 3, "dishes_t1_5_19": 3, "furniture_and_home_decor_t1_8_0": 4, "furniture_and_home_decor_t1_8_1": 4, "furniture_and_home_decor_t1_8_2": 4, "furniture_and_home_decor_t1_8_3": 4, "furniture_and_home_decor_t1_8_4": 4, "furniture_and_home_decor_t1_8_5": 4, "furniture_and_home_decor_t1_8_6": 4, "furniture_and_home_decor_t1_8_7": 4, "furniture_and_home_decor_t1_8_8": 4, "furniture_and_home_decor_t1_8_9": 4, "furniture_and_home_decor_t1_8_10": 4, "furniture_and_home_decor_t1_8_11": 4, "furniture_and_home_decor_t1_8_12": 4, "furniture_and_home_decor_t1_8_13": 4, "furniture_and_home_decor_t1_8_14": 4, "furniture_and_home_decor_t1_8_15": 4, "furniture_and_home_decor_t1_8_16": 4, "furniture_and_home_decor_t1_8_17": 4, "furniture_and_home_decor_t1_8_18": 4, "furniture_and_home_decor_t1_8_19": 4, "furniture_and_home_decor_t1_9_0": 4, "furniture_and_home_decor_t1_9_1": 4, "furniture_and_home_decor_t1_9_2": 4, "furniture_and_home_decor_t1_9_3": 4, "furniture_and_home_decor_t1_9_4": 4, "furniture_and_home_decor_t1_9_5": 4, "furniture_and_home_decor_t1_9_6": 4, "furniture_and_home_decor_t1_9_7": 4, "furniture_and_home_decor_t1_9_8": 4, "furniture_and_home_decor_t1_9_9": 4, "furniture_and_home_decor_t1_9_10": 4, "furniture_and_home_decor_t1_9_11": 4, "furniture_and_home_decor_t1_9_12": 4, "furniture_and_home_decor_t1_9_13": 4, "furniture_and_home_decor_t1_9_14": 4, "furniture_and_home_decor_t1_9_15": 4, "furniture_and_home_decor_t1_9_16": 4, "furniture_and_home_decor_t1_9_17": 4, "furniture_and_home_decor_t1_9_18": 4, "furniture_and_home_decor_t1_9_19": 4, "furniture_and_home_decor_t1_15_0": 4, "furniture_and_home_decor_t1_15_1": 4, "furniture_and_home_decor_t1_15_2": 4, "furniture_and_home_decor_t1_15_3": 4, "furniture_and_home_decor_t1_15_4": 4, "furniture_and_home_decor_t1_15_5": 4, "furniture_and_home_decor_t1_15_6": 4, "furniture_and_home_decor_t1_15_7": 4, "furniture_and_home_decor_t1_15_8": 4, "furniture_and_home_decor_t1_15_9": 4, "furniture_and_home_decor_t1_15_10": 4, "furniture_and_home_decor_t1_15_11": 4, "furniture_and_home_decor_t1_15_12": 4, "furniture_and_home_decor_t1_15_13": 4, "furniture_and_home_decor_t1_15_14": 4, "furniture_and_home_decor_t1_15_15": 4, "furniture_and_home_decor_t1_15_16": 4, "furniture_and_home_decor_t1_15_17": 4, "furniture_and_home_decor_t1_15_18": 4, "furniture_and_home_decor_t1_15_19": 4, "furniture_and_home_decor_t1_14_0": 4, "furniture_and_home_decor_t1_14_1": 4, "furniture_and_home_decor_t1_14_2": 4, "furniture_and_home_decor_t1_14_3": 4, "furniture_and_home_decor_t1_14_4": 4, "furniture_and_home_decor_t1_14_5": 4, "furniture_and_home_decor_t1_14_6": 4, "furniture_and_home_decor_t1_14_7": 4, "furniture_and_home_decor_t1_14_8": 4, "furniture_and_home_decor_t1_14_9": 4, "furniture_and_home_decor_t1_14_10": 4, "furniture_and_home_decor_t1_14_11": 4, "furniture_and_home_decor_t1_14_12": 4, "furniture_and_home_decor_t1_14_13": 4, "furniture_and_home_decor_t1_14_14": 4, "furniture_and_home_decor_t1_14_15": 4, "furniture_and_home_decor_t1_14_16": 4, "furniture_and_home_decor_t1_14_17": 4, "furniture_and_home_decor_t1_14_18": 4, "furniture_and_home_decor_t1_14_19": 4, "furniture_and_home_decor_t1_16_0": 4, "furniture_and_home_decor_t1_16_1": 4, "furniture_and_home_decor_t1_16_2": 4, "furniture_and_home_decor_t1_16_3": 4, "furniture_and_home_decor_t1_16_4": 4, "furniture_and_home_decor_t1_16_5": 4, "furniture_and_home_decor_t1_16_6": 4, "furniture_and_home_decor_t1_16_7": 4, "furniture_and_home_decor_t1_16_8": 4, "furniture_and_home_decor_t1_16_9": 4, "furniture_and_home_decor_t1_16_10": 4, "furniture_and_home_decor_t1_16_11": 4, "furniture_and_home_decor_t1_16_12": 4, "furniture_and_home_decor_t1_16_13": 4, "furniture_and_home_decor_t1_16_14": 4, "furniture_and_home_decor_t1_16_15": 4, "furniture_and_home_decor_t1_16_16": 4, "furniture_and_home_decor_t1_16_17": 4, "furniture_and_home_decor_t1_16_18": 4, "furniture_and_home_decor_t1_16_19": 4, "furniture_and_home_decor_t1_13_0": 4, "furniture_and_home_decor_t1_13_1": 4, "furniture_and_home_decor_t1_13_2": 4, "furniture_and_home_decor_t1_13_3": 4, "furniture_and_home_decor_t1_13_4": 4, "furniture_and_home_decor_t1_13_5": 4, "furniture_and_home_decor_t1_13_6": 4, "furniture_and_home_decor_t1_13_7": 4, "furniture_and_home_decor_t1_13_8": 4, "furniture_and_home_decor_t1_13_9": 4, "furniture_and_home_decor_t1_13_10": 4, "furniture_and_home_decor_t1_13_11": 4, "furniture_and_home_decor_t1_13_12": 4, "furniture_and_home_decor_t1_13_13": 4, "furniture_and_home_decor_t1_13_14": 4, "furniture_and_home_decor_t1_13_15": 4, "furniture_and_home_decor_t1_13_16": 4, "furniture_and_home_decor_t1_13_17": 4, "furniture_and_home_decor_t1_13_18": 4, "furniture_and_home_decor_t1_13_19": 4, "furniture_and_home_decor_t1_12_0": 4, "furniture_and_home_decor_t1_12_1": 4, "furniture_and_home_decor_t1_12_2": 4, "furniture_and_home_decor_t1_12_3": 4, "furniture_and_home_decor_t1_12_4": 4, "furniture_and_home_decor_t1_12_5": 4, "furniture_and_home_decor_t1_12_6": 4, "furniture_and_home_decor_t1_12_7": 4, "furniture_and_home_decor_t1_12_8": 4, "furniture_and_home_decor_t1_12_9": 4, "furniture_and_home_decor_t1_12_10": 4, "furniture_and_home_decor_t1_12_11": 4, "furniture_and_home_decor_t1_12_12": 4, "furniture_and_home_decor_t1_12_13": 4, "furniture_and_home_decor_t1_12_14": 4, "furniture_and_home_decor_t1_12_15": 4, "furniture_and_home_decor_t1_12_16": 4, "furniture_and_home_decor_t1_12_17": 4, "furniture_and_home_decor_t1_12_18": 4, "furniture_and_home_decor_t1_12_19": 4, "furniture_and_home_decor_t1_10_0": 4, "furniture_and_home_decor_t1_10_1": 4, "furniture_and_home_decor_t1_10_2": 4, "furniture_and_home_decor_t1_10_3": 4, "furniture_and_home_decor_t1_10_4": 4, "furniture_and_home_decor_t1_10_5": 4, "furniture_and_home_decor_t1_10_6": 4, "furniture_and_home_decor_t1_10_7": 4, "furniture_and_home_decor_t1_10_8": 4, "furniture_and_home_decor_t1_10_9": 4, "furniture_and_home_decor_t1_10_10": 4, "furniture_and_home_decor_t1_10_11": 4, "furniture_and_home_decor_t1_10_12": 4, "furniture_and_home_decor_t1_10_13": 4, "furniture_and_home_decor_t1_10_14": 4, "furniture_and_home_decor_t1_10_15": 4, "furniture_and_home_decor_t1_10_16": 4, "furniture_and_home_decor_t1_10_17": 4, "furniture_and_home_decor_t1_10_18": 4, "furniture_and_home_decor_t1_10_19": 4, "furniture_and_home_decor_t1_11_0": 4, "furniture_and_home_decor_t1_11_1": 4, "furniture_and_home_decor_t1_11_2": 4, "furniture_and_home_decor_t1_11_3": 4, "furniture_and_home_decor_t1_11_4": 4, "furniture_and_home_decor_t1_11_5": 4, "furniture_and_home_decor_t1_11_6": 4, "furniture_and_home_decor_t1_11_7": 4, "furniture_and_home_decor_t1_11_8": 4, "furniture_and_home_decor_t1_11_9": 4, "furniture_and_home_decor_t1_11_10": 4, "furniture_and_home_decor_t1_11_11": 4, "furniture_and_home_decor_t1_11_12": 4, "furniture_and_home_decor_t1_11_13": 4, "furniture_and_home_decor_t1_11_14": 4, "furniture_and_home_decor_t1_11_15": 4, "furniture_and_home_decor_t1_11_16": 4, "furniture_and_home_decor_t1_11_17": 4, "furniture_and_home_decor_t1_11_18": 4, "furniture_and_home_decor_t1_11_19": 4, "furniture_and_home_decor_t1_1_0": 4, "furniture_and_home_decor_t1_1_1": 4, "furniture_and_home_decor_t1_1_2": 4, "furniture_and_home_decor_t1_1_3": 4, "furniture_and_home_decor_t1_1_4": 4, "furniture_and_home_decor_t1_1_5": 4, "furniture_and_home_decor_t1_1_6": 4, "furniture_and_home_decor_t1_1_7": 4, "furniture_and_home_decor_t1_1_8": 4, "furniture_and_home_decor_t1_1_9": 4, "furniture_and_home_decor_t1_1_10": 4, "furniture_and_home_decor_t1_1_11": 4, "furniture_and_home_decor_t1_1_12": 4, "furniture_and_home_decor_t1_1_13": 4, "furniture_and_home_decor_t1_1_14": 4, "furniture_and_home_decor_t1_1_15": 4, "furniture_and_home_decor_t1_1_16": 4, "furniture_and_home_decor_t1_1_17": 4, "furniture_and_home_decor_t1_1_18": 4, "furniture_and_home_decor_t1_1_19": 4, "furniture_and_home_decor_t1_2_0": 4, "furniture_and_home_decor_t1_2_1": 4, "furniture_and_home_decor_t1_2_2": 4, "furniture_and_home_decor_t1_2_3": 4, "furniture_and_home_decor_t1_2_4": 4, "furniture_and_home_decor_t1_2_5": 4, "furniture_and_home_decor_t1_2_6": 4, "furniture_and_home_decor_t1_2_7": 4, "furniture_and_home_decor_t1_2_8": 4, "furniture_and_home_decor_t1_2_9": 4, "furniture_and_home_decor_t1_2_10": 4, "furniture_and_home_decor_t1_2_11": 4, "furniture_and_home_decor_t1_2_12": 4, "furniture_and_home_decor_t1_2_13": 4, "furniture_and_home_decor_t1_2_14": 4, "furniture_and_home_decor_t1_2_15": 4, "furniture_and_home_decor_t1_2_16": 4, "furniture_and_home_decor_t1_2_17": 4, "furniture_and_home_decor_t1_2_18": 4, "furniture_and_home_decor_t1_2_19": 4, "furniture_and_home_decor_t1_3_0": 4, "furniture_and_home_decor_t1_3_1": 4, "furniture_and_home_decor_t1_3_2": 4, "furniture_and_home_decor_t1_3_3": 4, "furniture_and_home_decor_t1_3_4": 4, "furniture_and_home_decor_t1_3_5": 4, "furniture_and_home_decor_t1_3_6": 4, "furniture_and_home_decor_t1_3_7": 4, "furniture_and_home_decor_t1_3_8": 4, "furniture_and_home_decor_t1_3_9": 4, "furniture_and_home_decor_t1_3_10": 4, "furniture_and_home_decor_t1_3_11": 4, "furniture_and_home_decor_t1_3_12": 4, "furniture_and_home_decor_t1_3_13": 4, "furniture_and_home_decor_t1_3_14": 4, "furniture_and_home_decor_t1_3_15": 4, "furniture_and_home_decor_t1_3_16": 4, "furniture_and_home_decor_t1_3_17": 4, "furniture_and_home_decor_t1_3_18": 4, "furniture_and_home_decor_t1_3_19": 4, "furniture_and_home_decor_t1_7_0": 4, "furniture_and_home_decor_t1_7_1": 4, "furniture_and_home_decor_t1_7_2": 4, "furniture_and_home_decor_t1_7_3": 4, "furniture_and_home_decor_t1_7_4": 4, "furniture_and_home_decor_t1_7_5": 4, "furniture_and_home_decor_t1_7_6": 4, "furniture_and_home_decor_t1_7_7": 4, "furniture_and_home_decor_t1_7_8": 4, "furniture_and_home_decor_t1_7_9": 4, "furniture_and_home_decor_t1_7_10": 4, "furniture_and_home_decor_t1_7_11": 4, "furniture_and_home_decor_t1_7_12": 4, "furniture_and_home_decor_t1_7_13": 4, "furniture_and_home_decor_t1_7_14": 4, "furniture_and_home_decor_t1_7_15": 4, "furniture_and_home_decor_t1_7_16": 4, "furniture_and_home_decor_t1_7_17": 4, "furniture_and_home_decor_t1_7_18": 4, "furniture_and_home_decor_t1_7_19": 4, "furniture_and_home_decor_t1_6_0": 4, "furniture_and_home_decor_t1_6_1": 4, "furniture_and_home_decor_t1_6_2": 4, "furniture_and_home_decor_t1_6_3": 4, "furniture_and_home_decor_t1_6_4": 4, "furniture_and_home_decor_t1_6_5": 4, "furniture_and_home_decor_t1_6_6": 4, "furniture_and_home_decor_t1_6_7": 4, "furniture_and_home_decor_t1_6_8": 4, "furniture_and_home_decor_t1_6_9": 4, "furniture_and_home_decor_t1_6_10": 4, "furniture_and_home_decor_t1_6_11": 4, "furniture_and_home_decor_t1_6_12": 4, "furniture_and_home_decor_t1_6_13": 4, "furniture_and_home_decor_t1_6_14": 4, "furniture_and_home_decor_t1_6_15": 4, "furniture_and_home_decor_t1_6_16": 4, "furniture_and_home_decor_t1_6_17": 4, "furniture_and_home_decor_t1_6_18": 4, "furniture_and_home_decor_t1_6_19": 4, "furniture_and_home_decor_t1_4_0": 4, "furniture_and_home_decor_t1_4_1": 4, "furniture_and_home_decor_t1_4_2": 4, "furniture_and_home_decor_t1_4_3": 4, "furniture_and_home_decor_t1_4_4": 4, "furniture_and_home_decor_t1_4_5": 4, "furniture_and_home_decor_t1_4_6": 4, "furniture_and_home_decor_t1_4_7": 4, "furniture_and_home_decor_t1_4_8": 4, "furniture_and_home_decor_t1_4_9": 4, "furniture_and_home_decor_t1_4_10": 4, "furniture_and_home_decor_t1_4_11": 4, "furniture_and_home_decor_t1_4_12": 4, "furniture_and_home_decor_t1_4_13": 4, "furniture_and_home_decor_t1_4_14": 4, "furniture_and_home_decor_t1_4_15": 4, "furniture_and_home_decor_t1_4_16": 4, "furniture_and_home_decor_t1_4_17": 4, "furniture_and_home_decor_t1_4_18": 4, "furniture_and_home_decor_t1_4_19": 4, "furniture_and_home_decor_t1_5_0": 4, "furniture_and_home_decor_t1_5_1": 4, "furniture_and_home_decor_t1_5_2": 4, "furniture_and_home_decor_t1_5_3": 4, "furniture_and_home_decor_t1_5_4": 4, "furniture_and_home_decor_t1_5_5": 4, "furniture_and_home_decor_t1_5_6": 4, "furniture_and_home_decor_t1_5_7": 4, "furniture_and_home_decor_t1_5_8": 4, "furniture_and_home_decor_t1_5_9": 4, "furniture_and_home_decor_t1_5_10": 4, "furniture_and_home_decor_t1_5_11": 4, "furniture_and_home_decor_t1_5_12": 4, "furniture_and_home_decor_t1_5_13": 4, "furniture_and_home_decor_t1_5_14": 4, "furniture_and_home_decor_t1_5_15": 4, "furniture_and_home_decor_t1_5_16": 4, "furniture_and_home_decor_t1_5_17": 4, "furniture_and_home_decor_t1_5_18": 4, "furniture_and_home_decor_t1_5_19": 4, "others_t1_8_0": 5, "others_t1_8_1": 5, "others_t1_8_2": 5, "others_t1_8_3": 5, "others_t1_8_4": 5, "others_t1_8_5": 5, "others_t1_8_6": 5, "others_t1_8_7": 5, "others_t1_8_8": 5, "others_t1_8_9": 5, "others_t1_8_10": 5, "others_t1_8_11": 5, "others_t1_8_12": 5, "others_t1_8_13": 5, "others_t1_8_14": 5, "others_t1_8_15": 5, "others_t1_8_16": 5, "others_t1_8_17": 5, "others_t1_8_18": 5, "others_t1_8_19": 5, "others_t1_9_0": 5, "others_t1_9_1": 5, "others_t1_9_2": 5, "others_t1_9_3": 5, "others_t1_9_4": 5, "others_t1_9_5": 5, "others_t1_9_6": 5, "others_t1_9_7": 5, "others_t1_9_8": 5, "others_t1_9_9": 5, "others_t1_9_10": 5, "others_t1_9_11": 5, "others_t1_9_12": 5, "others_t1_9_13": 5, "others_t1_9_14": 5, "others_t1_9_15": 5, "others_t1_9_16": 5, "others_t1_9_17": 5, "others_t1_9_18": 5, "others_t1_9_19": 5, "others_t1_12_0": 5, "others_t1_12_1": 5, "others_t1_12_2": 5, "others_t1_12_3": 5, "others_t1_12_4": 5, "others_t1_12_5": 5, "others_t1_12_6": 5, "others_t1_12_7": 5, "others_t1_12_8": 5, "others_t1_12_9": 5, "others_t1_12_10": 5, "others_t1_12_11": 5, "others_t1_12_12": 5, "others_t1_12_13": 5, "others_t1_12_14": 5, "others_t1_12_15": 5, "others_t1_12_16": 5, "others_t1_12_17": 5, "others_t1_12_18": 5, "others_t1_12_19": 5, "others_t1_10_0": 5, "others_t1_10_1": 5, "others_t1_10_2": 5, "others_t1_10_3": 5, "others_t1_10_4": 5, "others_t1_10_5": 5, "others_t1_10_6": 5, "others_t1_10_7": 5, "others_t1_10_8": 5, "others_t1_10_9": 5, "others_t1_10_10": 5, "others_t1_10_11": 5, "others_t1_10_12": 5, "others_t1_10_13": 5, "others_t1_10_14": 5, "others_t1_10_15": 5, "others_t1_10_16": 5, "others_t1_10_17": 5, "others_t1_10_18": 5, "others_t1_10_19": 5, "others_t1_11_0": 5, "others_t1_11_1": 5, "others_t1_11_2": 5, "others_t1_11_3": 5, "others_t1_11_4": 5, "others_t1_11_5": 5, "others_t1_11_6": 5, "others_t1_11_7": 5, "others_t1_11_8": 5, "others_t1_11_9": 5, "others_t1_11_10": 5, "others_t1_11_11": 5, "others_t1_11_12": 5, "others_t1_11_13": 5, "others_t1_11_14": 5, "others_t1_11_15": 5, "others_t1_11_16": 5, "others_t1_11_17": 5, "others_t1_11_18": 5, "others_t1_11_19": 5, "others_t1_1_0": 5, "others_t1_1_1": 5, "others_t1_1_2": 5, "others_t1_1_3": 5, "others_t1_1_4": 5, "others_t1_1_5": 5, "others_t1_1_6": 5, "others_t1_1_7": 5, "others_t1_1_8": 5, "others_t1_1_9": 5, "others_t1_1_10": 5, "others_t1_1_11": 5, "others_t1_1_12": 5, "others_t1_1_13": 5, "others_t1_1_14": 5, "others_t1_1_15": 5, "others_t1_1_16": 5, "others_t1_1_17": 5, "others_t1_1_18": 5, "others_t1_1_19": 5, "others_t1_2_0": 5, "others_t1_2_1": 5, "others_t1_2_2": 5, "others_t1_2_3": 5, "others_t1_2_4": 5, "others_t1_2_5": 5, "others_t1_2_6": 5, "others_t1_2_7": 5, "others_t1_2_8": 5, "others_t1_2_9": 5, "others_t1_2_10": 5, "others_t1_2_11": 5, "others_t1_2_12": 5, "others_t1_2_13": 5, "others_t1_2_14": 5, "others_t1_2_15": 5, "others_t1_2_16": 5, "others_t1_2_17": 5, "others_t1_2_18": 5, "others_t1_2_19": 5, "others_t1_3_0": 5, "others_t1_3_1": 5, "others_t1_3_2": 5, "others_t1_3_3": 5, "others_t1_3_4": 5, "others_t1_3_5": 5, "others_t1_3_6": 5, "others_t1_3_7": 5, "others_t1_3_8": 5, "others_t1_3_9": 5, "others_t1_3_10": 5, "others_t1_3_11": 5, "others_t1_3_12": 5, "others_t1_3_13": 5, "others_t1_3_14": 5, "others_t1_3_15": 5, "others_t1_3_16": 5, "others_t1_3_17": 5, "others_t1_3_18": 5, "others_t1_3_19": 5, "others_t1_7_0": 5, "others_t1_7_1": 5, "others_t1_7_2": 5, "others_t1_7_3": 5, "others_t1_7_4": 5, "others_t1_7_5": 5, "others_t1_7_6": 5, "others_t1_7_7": 5, "others_t1_7_8": 5, "others_t1_7_9": 5, "others_t1_7_10": 5, "others_t1_7_11": 5, "others_t1_7_12": 5, "others_t1_7_13": 5, "others_t1_7_14": 5, "others_t1_7_15": 5, "others_t1_7_16": 5, "others_t1_7_17": 5, "others_t1_7_18": 5, "others_t1_7_19": 5, "others_t1_6_0": 5, "others_t1_6_1": 5, "others_t1_6_2": 5, "others_t1_6_3": 5, "others_t1_6_4": 5, "others_t1_6_5": 5, "others_t1_6_6": 5, "others_t1_6_7": 5, "others_t1_6_8": 5, "others_t1_6_9": 5, "others_t1_6_10": 5, "others_t1_6_11": 5, "others_t1_6_12": 5, "others_t1_6_13": 5, "others_t1_6_14": 5, "others_t1_6_15": 5, "others_t1_6_16": 5, "others_t1_6_17": 5, "others_t1_6_18": 5, "others_t1_6_19": 5, "others_t1_4_0": 5, "others_t1_4_1": 5, "others_t1_4_2": 5, "others_t1_4_3": 5, "others_t1_4_4": 5, "others_t1_4_5": 5, "others_t1_4_6": 5, "others_t1_4_7": 5, "others_t1_4_8": 5, "others_t1_4_9": 5, "others_t1_4_10": 5, "others_t1_4_11": 5, "others_t1_4_12": 5, "others_t1_4_13": 5, "others_t1_4_14": 5, "others_t1_4_15": 5, "others_t1_4_16": 5, "others_t1_4_17": 5, "others_t1_4_18": 5, "others_t1_4_19": 5, "others_t1_5_0": 5, "others_t1_5_1": 5, "others_t1_5_2": 5, "others_t1_5_3": 5, "others_t1_5_4": 5, "others_t1_5_5": 5, "others_t1_5_6": 5, "others_t1_5_7": 5, "others_t1_5_8": 5, "others_t1_5_9": 5, "others_t1_5_10": 5, "others_t1_5_11": 5, "others_t1_5_12": 5, "others_t1_5_13": 5, "others_t1_5_14": 5, "others_t1_5_15": 5, "others_t1_5_16": 5, "others_t1_5_17": 5, "others_t1_5_18": 5, "others_t1_5_19": 5}
